asphalt/mailer/__init__.py
asphalt/mailer/api.py
asphalt/mailer/component.py
asphalt/mailer/py.typed
asphalt/mailer/utils.py
asphalt/mailer/mailers/__init__.py
asphalt/mailer/mailers/mock.py
asphalt/mailer/mailers/sendmail.py
asphalt/mailer/mailers/smtp.py
asphalt_mailer-4.0.0.dist-info/LICENSE
asphalt_mailer-4.0.0.dist-info/METADATA
asphalt_mailer-4.0.0.dist-info/WHEEL
asphalt_mailer-4.0.0.dist-info/entry_points.txt
asphalt_mailer-4.0.0.dist-info/top_level.txt
asphalt_mailer-4.0.0.dist-info/RECORD
