Metadata-Version: 2.1
Name: asphalt-mailer
Version: 4.0.0
Summary: Mailer component for the Asphalt framework
Author-email: Alex Grönholm <alex.gronholm@nextday.fi>
License: Apache License 2.0
Project-URL: Homepage, https://github.com/asphalt-framework/asphalt-mailer
Classifier: Development Status :: 5 - Production/Stable
Classifier: Intended Audience :: Developers
Classifier: License :: OSI Approved :: Apache Software License
Classifier: Topic :: Communications :: Email
Classifier: Programming Language :: Python
Classifier: Programming Language :: Python :: 3
Classifier: Programming Language :: Python :: 3.7
Classifier: Programming Language :: Python :: 3.8
Classifier: Programming Language :: Python :: 3.9
Classifier: Programming Language :: Python :: 3.10
Classifier: Programming Language :: Python :: 3.11
Requires-Python: >=3.7
License-File: LICENSE
Requires-Dist: asphalt (~=4.8)
Requires-Dist: aiosmtplib (~=2.0)
Provides-Extra: doc
Requires-Dist: Sphinx (>=1.5) ; extra == 'doc'
Requires-Dist: sphinx-rtd-theme ; extra == 'doc'
Requires-Dist: sphinx-autodoc-typehints (>=1.2.0) ; extra == 'doc'
Requires-Dist: sphinxcontrib-asyncio (>=0.2.0) ; extra == 'doc'
Provides-Extra: test
Requires-Dist: aiosmtpd ; extra == 'test'
Requires-Dist: anyio (>=3.6.1) ; extra == 'test'
Requires-Dist: pytest ; extra == 'test'
Requires-Dist: trustme ; extra == 'test'
